pyvoicelib/__init__.py
pyvoicelib/constants.py
pyvoicelib/core.py
pyvoicelib/exceptions.py
pyvoicelib/utils.py
pyvoicelib-0.1.5.dist-info/licenses/LICENSE
tests/__init__.py
tests/conftest.py
tests/test_core.py
pyvoicelib-0.1.5.dist-info/METADATA
pyvoicelib-0.1.5.dist-info/WHEEL
pyvoicelib-0.1.5.dist-info/top_level.txt
pyvoicelib-0.1.5.dist-info/RECORD
